Metadata-Version: 2.1
Name: moodle-kit
Version: 0.1.7
Summary: A simple Python package with some functionalities to interact with moodle-based LMS.
Home-page: https://github.com/ahmadfebrianto/moodle-kit
Author: Ahmad Febrianto
Author-email: achmadfebryanto@gmail.com
License: GNU General Public License v3.0
Download-URL: https://github.com/ahmadfebrianto/moodle-kit/archive/v0.1.7.tar.gz
Keywords: moodle
Platform: UNKNOWN
Classifier: Development Status :: 5 - Production/Stable
Classifier: Intended Audience :: Developers
Classifier: Topic :: Software Development :: Build Tools
Classifier: Programming Language :: Python :: 3.6
